LICENSE
README.md
setup.cfg
setup.py
pfilter/__init__.py
pfilter/pfilter.py
pfilter.egg-info/PKG-INFO
pfilter.egg-info/SOURCES.txt
pfilter.egg-info/dependency_links.txt
pfilter.egg-info/requires.txt
pfilter.egg-info/top_level.txt