Metadata-Version: 2.1
Name: pfilter
Version: 0.2.5
Summary: A basic particle filter
Home-page: https://github.com/johnhw/pfilter
Author: John H Williamson
Author-email: johnhw@gmail.com
License: UNKNOWN
Download-URL: https://github.com/johnhw/pfilter/tarball/0.2.5
Keywords: particle,probabilistic,stochastic,filter,filtering
Platform: UNKNOWN
License-File: LICENSE
